mockquerpy/__init__.py
mockquerpy/mockquerpy.py
mockquerpy/mockquerpy_mocks.py
mockquerpy/test_mockquery.py
mockquerpy/wrapper.py
mockquerpy-0.1.0.dist-info/LICENSE
mockquerpy-0.1.0.dist-info/METADATA
mockquerpy-0.1.0.dist-info/WHEEL
mockquerpy-0.1.0.dist-info/top_level.txt
mockquerpy-0.1.0.dist-info/RECORD
