Metadata-Version: 2.1
Name: mockquerpy
Version: 0.1.0
Summary: A google bigquery client library mocker
Home-page: https://gitlab.com/peakbreaker/MockQuerPy
Author: peakbreaker
Author-email: andershurum@gmail.compile
License: UNKNOWN
Platform: UNKNOWN
Classifier: Programming Language :: Python :: 3
Classifier: License :: OSI Approved :: MIT License
Classifier: Operating System :: OS Independent
